image_processing/__init__.py
image_processing/processing/__init__.py
image_processing/processing/combination.py
image_processing/processing/transformation.py
image_processing/utils/__init__.py
image_processing/utils/io.py
image_processing/utils/plot.py
my_image_processing-0.0.3.dist-info/LICENSE.txt
my_image_processing-0.0.3.dist-info/METADATA
my_image_processing-0.0.3.dist-info/WHEEL
my_image_processing-0.0.3.dist-info/top_level.txt
my_image_processing-0.0.3.dist-info/RECORD
