Metadata-Version: 2.1
Name: my-image-processing
Version: 0.0.3
Summary: Image processing package using Skimage
Home-page: https://github.com/wilsondesouza/image-processing-package
Author: Wilson Souza
Requires-Python: >=3.5
License-File: LICENSE.txt
Requires-Dist: matplotlib
Requires-Dist: numpy
Requires-Dist: scikit-image >=0.16.1
